mann/__init__.py
mann/burning/__init__.py
mann/burning/layers/Conv2D.py
mann/burning/layers/Dense.py
mann/burning/layers/FilterLayer.py
mann/burning/layers/MaskedConv2D.py
mann/burning/layers/MaskedDense.py
mann/burning/layers/MultiConv2D.py
mann/burning/layers/MultiDense.py
mann/burning/layers/MultiMaskedConv2D.py
mann/burning/layers/MultiMaskedDense.py
mann/burning/layers/SelectorLayer.py
mann/burning/layers/SparseConv2D.py
mann/burning/layers/SparseDense.py
mann/burning/layers/SparseMultiConv2D.py
mann/burning/layers/SparseMultiDense.py
mann/burning/layers/__init__.py
mann/layers/FilterLayer.py
mann/layers/MaskedConv2D.py
mann/layers/MaskedDense.py
mann/layers/MultiConv2D.py
mann/layers/MultiDense.py
mann/layers/MultiMaskedConv2D.py
mann/layers/MultiMaskedDense.py
mann/layers/MultiMaxPool2D.py
mann/layers/SelectorLayer.py
mann/layers/SumLayer.py
mann/layers/__init__.py
mann/utils/ActiveSparsification.py
mann/utils/__init__.py
mann/utils/transformer.py
mann/utils/utils.py
mann-0.3.0.dist-info/LICENSE
mann-0.3.0.dist-info/METADATA
mann-0.3.0.dist-info/WHEEL
mann-0.3.0.dist-info/top_level.txt
mann-0.3.0.dist-info/RECORD
