Metadata-Version: 2.1
Name: mann
Version: 0.3.0
Summary: Package containing utilities for implementing RSN2/MANN
Home-page: https://github.com/AISquaredInc/mann
Author: The AI Squared Team
Author-email: mann@squared.ai
License: Apache 2.0
License-File: LICENSE
Requires-Dist: tensorflow (>=2.4)
Requires-Dist: torch
